odoo/addons/purchase_receipt_percentage/README.rst
odoo/addons/purchase_receipt_percentage/__init__.py
odoo/addons/purchase_receipt_percentage/__manifest__.py
odoo/addons/purchase_receipt_percentage/i18n/es.po
odoo/addons/purchase_receipt_percentage/i18n/fr.po
odoo/addons/purchase_receipt_percentage/i18n/purchase_receipt_percentage.pot
odoo/addons/purchase_receipt_percentage/models/__init__.py
odoo/addons/purchase_receipt_percentage/models/purchase_order.py
odoo/addons/purchase_receipt_percentage/models/purchase_order_line.py
odoo/addons/purchase_receipt_percentage/readme/CONTRIBUTORS.rst
odoo/addons/purchase_receipt_percentage/readme/DESCRIPTION.rst
odoo/addons/purchase_receipt_percentage/static/description/icon.png
odoo/addons/purchase_receipt_percentage/static/description/index.html
odoo/addons/purchase_receipt_percentage/tests/__init__.py
odoo/addons/purchase_receipt_percentage/tests/test_purchase_receipt_percentage.py
odoo/addons/purchase_receipt_percentage/views/purchase_order.xml
odoo_addon_purchase_receipt_percentage-15.0.1.0.0.7.dist-info/METADATA
odoo_addon_purchase_receipt_percentage-15.0.1.0.0.7.dist-info/WHEEL
odoo_addon_purchase_receipt_percentage-15.0.1.0.0.7.dist-info/top_level.txt
odoo_addon_purchase_receipt_percentage-15.0.1.0.0.7.dist-info/RECORD
